abfe/__init__.py
abfe/_version.py
abfe/calculate_abfe.py
abfe/calculate_abfe_gmx.py
abfe/conf.py
abfe/orchestration/__init__.py
abfe/orchestration/build_approach_flow.py
abfe/orchestration/build_ligand_flow.py
abfe/orchestration/generate_conf.py
abfe/orchestration/generate_scheduler.py
abfe/orchestration/generate_snake.py
abfe/rules/__init__.py
abfe/rules/ligand_equilibration_workflow/Snakefile.smk
abfe/rules/ligand_equilibration_workflow/complex_equil_setup.smk
abfe/rules/ligand_equilibration_workflow/complex_equil_simulation.smk
abfe/rules/ligand_equilibration_workflow/ligand_equil_setup.smk
abfe/rules/ligand_equilibration_workflow/ligand_equil_simulation.smk
abfe/rules/ligand_fep_workflow/Snakefile.smk
abfe/rules/ligand_fep_workflow/calculate_result.smk
abfe/rules/ligand_fep_workflow/complex_fep_ana.smk
abfe/rules/ligand_fep_workflow/complex_fep_setup.smk
abfe/rules/ligand_fep_workflow/complex_fep_simulation.smk
abfe/rules/ligand_fep_workflow/ligand_fep_ana.smk
abfe/rules/ligand_fep_workflow/ligand_fep_setup.smk
abfe/rules/ligand_fep_workflow/ligand_fep_simulation.smk
abfe/rules/receptor_workflow/Snakefile.smk
abfe/rules/receptor_workflow/Snakefile_gmx.smk
abfe/rules/receptor_workflow/build_ligand_systems.smk
abfe/rules/receptor_workflow/post_commands.smk
abfe/rules/receptor_workflow/simulations.smk
abfe/scripts/__init__.py
abfe/scripts/abfe_slurm_status.py
abfe/scripts/final_receptor_results.py
abfe/scripts/free_energy/__init__.py
abfe/scripts/free_energy/alchemlyb_analysis.py
abfe/scripts/free_energy/calculate_ABFE_ligand_dG.py
abfe/scripts/free_energy/calculate_ABFE_transformation_dG.py
abfe/scripts/preparation/__init__.py
abfe/scripts/preparation/generate_ABFE_systems.py
abfe/scripts/preparation/generate_boresch_restraints.py
abfe/scripts/preparation/parametrize.py
abfe/scripts/preparation/topology_fixer.py
abfe/template/__init__.py
abfe/template/complex_equil_workflow/emin/emin.mdp
abfe/template/complex_equil_workflow/npt_equil1/npt_equil1.mdp
ABFE_Workflow-0.5.0.dist-info/LICENSE
ABFE_Workflow-0.5.0.dist-info/METADATA
ABFE_Workflow-0.5.0.dist-info/WHEEL
ABFE_Workflow-0.5.0.dist-info/entry_points.txt
ABFE_Workflow-0.5.0.dist-info/top_level.txt
ABFE_Workflow-0.5.0.dist-info/RECORD
