Metadata-Version: 2.1
Name: ABFE_Workflow
Version: 0.5.0
Summary: ABFE Workflow is a pipeline variant of our prior work.
Author: Irfan Alibay
Author-email: Benjamin Ries <benjamin.ries@boehringer-ingelheim.com>, Philip Biggins <philip.biggin@bioch.ox.ac.uk>, Aniket Magarkar <aniket.magarkar@boehringer-ingelheim.com>
Project-URL: Homepage, https://github.com/bigginlab/ABFE_workflow
Classifier: Programming Language :: Python :: 3
Classifier: License :: OSI Approved :: MIT License
Classifier: Operating System :: OS Independent
Requires-Python: >=3.9
License-File: LICENSE
Requires-Dist: snakemake
Requires-Dist: pymbar
Requires-Dist: alchemlyb
Requires-Dist: gromacs
Requires-Dist: scipy
Requires-Dist: numpy
Requires-Dist: pandas
Requires-Dist: matplotlib
Requires-Dist: argparse
